pdf2md/__init__.py
pdf2md/parser.py
pdf2md/pile.py
pdf2md/syntax.py
pdf2md/writer.py
pdf_to_markdown-0.1.0.data/scripts/pdf2md
pdf_to_markdown-0.1.0.dist-info/METADATA
pdf_to_markdown-0.1.0.dist-info/RECORD
pdf_to_markdown-0.1.0.dist-info/WHEEL
pdf_to_markdown-0.1.0.dist-info/top_level.txt
