Metadata-Version: 2.1
Name: pdf-to-markdown
Version: 0.1.0
Summary: Convert PDF files into markdown files
Home-page: https://github.com/johnlinp/pdf-to-markdown
Author: johnlinp
Author-email: johnlinp@gmail.com
License: New BSD License
Platform: UNKNOWN
Requires-Dist: pdfminer.six
